odoo/addons/sm_partago_invoicing_rest_api/__init__.py
odoo/addons/sm_partago_invoicing_rest_api/__manifest__.py
odoo/addons/sm_partago_invoicing_rest_api/models/__init__.py
odoo/addons/sm_partago_invoicing_rest_api/models/models_sm_company.py
odoo/addons/sm_partago_invoicing_rest_api/models/models_sm_res_config_settings.py
odoo/addons/sm_partago_invoicing_rest_api/services/__init__.py
odoo/addons/sm_partago_invoicing_rest_api/services/cs_invoice_services.py
odoo/addons/sm_partago_invoicing_rest_api/services/schemas.py
odoo/addons/sm_partago_invoicing_rest_api/tests/__init__.py
odoo/addons/sm_partago_invoicing_rest_api/tests/test_cs_auto_invoice_registration_and_payment.py
odoo/addons/sm_partago_invoicing_rest_api/tests/test_cs_invoice_services.py
odoo/addons/sm_partago_invoicing_rest_api/views/views_res_config_settings.xml
odoo12_addon_sm_partago_invoicing_rest_api-12.0.0.3.0.dist-info/METADATA
odoo12_addon_sm_partago_invoicing_rest_api-12.0.0.3.0.dist-info/WHEEL
odoo12_addon_sm_partago_invoicing_rest_api-12.0.0.3.0.dist-info/top_level.txt
odoo12_addon_sm_partago_invoicing_rest_api-12.0.0.3.0.dist-info/RECORD
