Metadata-Version: 2.2
Name: odoo12-addon-sm_partago_invoicing_rest_api
Version: 12.0.0.3.0
Summary: Expose CS Invoice with REST API
Home-page: https://git.coopdevs.org/coopdevs/odoo/odoo-addons/enhancements/enhancements-account-invoicing
Author: Coopdevs Treball
Classifier: Programming Language :: Python
Classifier: Framework :: Odoo
Classifier: Framework :: Odoo :: 12.0
Requires-Python: >=3.5
Requires-Dist: odoo12-addon-base_rest_base_structure
Requires-Dist: odoo12-addon-sm_partago_invoicing
Requires-Dist: odoo<12.1dev,>=12.0a
Dynamic: author
Dynamic: classifier
Dynamic: description
Dynamic: home-page
Dynamic: requires-dist
Dynamic: requires-python
Dynamic: summary
